datacheck/__init__.py
datacheck/__main__.py
datacheck/airflow/__init__.py
datacheck/airflow/operators.py
datacheck/cli.py
datacheck/config.py
datacheck/connectors/__init__.py
datacheck/connectors/azure.py
datacheck/connectors/base.py
datacheck/connectors/cloud_base.py
datacheck/connectors/gcs.py
datacheck/connectors/mssql.py
datacheck/connectors/mysql.py
datacheck/connectors/postgresql.py
datacheck/connectors/s3.py
datacheck/dbt/__init__.py
datacheck/dbt/test_converter.py
datacheck/docs/cloud-storage.md
datacheck/engine.py
datacheck/examples/cloud_storage/s3/README.md
datacheck/examples/cloud_storage/s3/config_example.yaml
datacheck/examples/cloud_storage/s3/s3_basic_example.py
datacheck/examples/cloud_storage/s3/s3_batch_validation.py
datacheck/exceptions.py
datacheck/loader.py
datacheck/notifications/__init__.py
datacheck/notifications/slack.py
datacheck/output.py
datacheck/parallel/__init__.py
datacheck/parallel/executor.py
datacheck/plugins/__init__.py
datacheck/plugins/decorators.py
datacheck/plugins/loader.py
datacheck/plugins/registry.py
datacheck/profiling/__init__.py
datacheck/profiling/profiler.py
datacheck/results.py
datacheck/rules.py
datacheck/sampling/__init__.py
datacheck/sampling/sampler.py
datacheck/streaming/__init__.py
datacheck/streaming/chunked_reader.py
datacheck/streaming/progress.py
datacheck/streaming/streaming_validator.py
datacheck/validation/__init__.py
datacheck/validation/config.py
datacheck/validation/rules.py
datacheck/validation/validator.py
datacheck_cli-1.1.0.dist-info/METADATA
datacheck_cli-1.1.0.dist-info/WHEEL
datacheck_cli-1.1.0.dist-info/entry_points.txt
datacheck_cli-1.1.0.dist-info/licenses/LICENSE
datacheck_cli-1.1.0.dist-info/RECORD
