Metadata-Version: 2.4
Name: datacheck-cli
Version: 1.1.0
Summary: CLI-first data validation tool for data engineers. Catch bad data before it breaks pipelines.
License: Apache-2.0
License-File: LICENSE
Keywords: data-validation,cli,data-engineering,pipeline,ci-cd,data-quality,yaml,testing,csv,parquet,postgres,data-testing
Author: Squrtech
Author-email: contact@squrtech.com
Requires-Python: >=3.10,<4.0
Classifier: Development Status :: 5 - Production/Stable
Classifier: Intended Audience :: Developers
Classifier: License :: OSI Approved :: Apache Software License
Classifier: Programming Language :: Python :: 3
Classifier: Programming Language :: Python :: 3.10
Classifier: Programming Language :: Python :: 3.11
Classifier: Programming Language :: Python :: 3.12
Classifier: Programming Language :: Python :: 3.13
Classifier: Programming Language :: Python :: 3.14
Provides-Extra: all
Provides-Extra: cloud
Provides-Extra: duckdb
Provides-Extra: mssql
Provides-Extra: mysql
Provides-Extra: postgres
Provides-Extra: postgresql
Requires-Dist: azure-storage-blob (>=12.19.0,<13.0.0) ; extra == "cloud" or extra == "all"
Requires-Dist: boto3 (>=1.34.0,<2.0.0) ; extra == "cloud" or extra == "all"
Requires-Dist: click (>=8.1.0,<8.2.0)
Requires-Dist: duckdb (>=0.8.1,<2.0.0) ; (platform_system != "Windows") and (extra == "duckdb" or extra == "all")
Requires-Dist: google-cloud-storage (>=2.14.0,<3.0.0) ; extra == "cloud" or extra == "all"
Requires-Dist: mysql-connector-python (>=8.2.0,<10.0.0) ; extra == "mysql" or extra == "all"
Requires-Dist: pandas (>=2.0.0,<3.0.0)
Requires-Dist: psycopg2-binary (>=2.9.9,<3.0.0) ; extra == "postgresql" or extra == "postgres" or extra == "all"
Requires-Dist: pyarrow (>=22.0.0,<24.0.0)
Requires-Dist: pyodbc (>=5.0.1,<6.0.0) ; extra == "mssql" or extra == "all"
Requires-Dist: pyyaml (>=6.0,<7.0)
Requires-Dist: rich (>=13,<15)
Requires-Dist: sqlalchemy (>=2.0.23,<3.0.0)
Requires-Dist: typer (>=0.12,<0.22)
Project-URL: Homepage, https://github.com/squrtech/datacheck
Project-URL: Repository, https://github.com/squrtech/datacheck
